<?xml version="1.0" ?>
<VNCLASS id="sở hữu">
	<MEMBERS>
		<MEMBER name="sở hữu" sense="sở hữu"/>
	</MEMBERS>
	<THEMROLES/>
	<FRAMES/>
	<SUBCLASSES>
		<VNCLASS id="sở hữu-40">
			<MEMBERS/>
			<THEMROLES/>
			<FRAMES/>
			<SUBCLASSES>
				<VNCLASS id="sở hữu-40.1">
					<MEMBERS>
						<MEMBER name="sở hữu" sense="sở hữu"/>
					</MEMBERS>
					<THEMROLES>
						<THEMROLE type="Pivot">
							<SELRESTRS/>
						</THEMROLE>
						<THEMROLE type="Theme">
							<SELRESTRS/>
						</THEMROLE>
					</THEMROLES>
					<FRAMES>
						<FRAME description="Pivot V Theme">
							<SYNTAX>
								<syntaxItems accepted="" type="ThemRole" value="Pivot"/>
								<syntaxItems accepted="" type="Verb" value="V"/>
								<syntaxItems accepted="" type="ThemRole" value="Theme"/>
							</SYNTAX>
							<SEMANTICS>
								<semanticItems value="has_possession" negative="-">
									<ARGS>
										<args type="Event" optional="false" value="E"/>
										<args type="ThemRole" optional="false" value="Pivot"/>
										<args type="ThemRole" optional="false" value="Theme"/>
									</ARGS>
								</semanticItems>
							</SEMANTICS>
							<EXAMPLES>
								<EXAMPLE>sở hữu tư liệu sản xuất</EXAMPLE>
							</EXAMPLES>
						</FRAME>
					</FRAMES>
				</VNCLASS>
				<VNCLASS id="sở hữu-40.2">
					<MEMBERS>
						<MEMBER name="có" sense="có"/>
					</MEMBERS>
					<THEMROLES>
						<THEMROLE type="Pivot">
							<SELRESTRS/>
						</THEMROLE>
						<THEMROLE type="Theme">
							<SELRESTRS/>
						</THEMROLE>
					</THEMROLES>
					<FRAMES>
						<FRAME description="Pivot V Theme">
							<SYNTAX>
								<syntaxItems accepted="" type="ThemRole" value="Pivot"/>
								<syntaxItems accepted="" type="Verb" value="V"/>
								<syntaxItems accepted="" type="ThemRole" value="Theme"/>
							</SYNTAX>
							<SEMANTICS>
								<semanticItems value="has_possession" negative="-">
									<ARGS>
										<args type="Event" optional="false" value="E"/>
										<args type="ThemRole" optional="false" value="Pivot"/>
										<args type="ThemRole" optional="false" value="Theme"/>
									</ARGS>
								</semanticItems>
							</SEMANTICS>
							<EXAMPLES>
								<EXAMPLE>ngoài cửa sổ có bóng người</EXAMPLE>
							</EXAMPLES>
						</FRAME>
					</FRAMES>
				</VNCLASS>
			</SUBCLASSES>
		</VNCLASS>
	</SUBCLASSES>
</VNCLASS>
