<?xml version="1.0" ?>
<VNCLASS id="đánh cược (rủi ro)">
	<MEMBERS>
		<MEMBER name="đánh cược" sense="đánh cược"/>
	</MEMBERS>
	<THEMROLES/>
	<FRAMES/>
	<SUBCLASSES>
		<VNCLASS id="đánh cược-57">
			<MEMBERS>
				<MEMBER name="cá cược" sense="cá cược"/>
				<MEMBER name="cá độ" sense="cá độ"/>
				<MEMBER name="cược" sense="cược"/>
				<MEMBER name="đặt cược" sense="đặt cược"/>
				<MEMBER name="đánh cược" sense="đánh cược"/>
				<MEMBER name="đánh cuộc" sense="đánh cuộc"/>
			</MEMBERS>
			<THEMROLES>
				<THEMROLE type="Agent">
					<SELRESTRS/>
				</THEMROLE>
				<THEMROLE type="Theme">
					<SELRESTRS/>
				</THEMROLE>
			</THEMROLES>
			<FRAMES>
				<FRAME description="Agent V Theme">
					<SYNTAX>
						<syntaxItems accepted="" type="ThemRole" value="Agent"/>
						<syntaxItems accepted="" type="Verb" value="V"/>
						<syntaxItems accepted="" type="ThemRole" value="Theme"/>
					</SYNTAX>
					<SEMANTICS>
						<semanticItems value="risk" negative="-">
							<ARGS>
								<args type="Event" optional="false" value="during(E)"/>
								<args type="ThemRole" optional="false" value="Agent"/>
								<args type="ThemRole" optional="false" value="Theme"/>
							</ARGS>
						</semanticItems>
					</SEMANTICS>
					<EXAMPLES>
						<EXAMPLE>Hắn đặt cược một ngôi nhà</EXAMPLE>
					</EXAMPLES>
				</FRAME>
			</FRAMES>
		</VNCLASS>
	</SUBCLASSES>
</VNCLASS>
